{
  "optimizer": "adamw",
  "seed": 0,
  "target_acc": 0.94,
  "steps_to_target": null,
  "train_time_to_target_s": null,
  "final_acc": 0.9285,
  "best_acc": 0.9285,
  "total_train_time_s": 232.72,
  "total_wall_time_s": 292.811,
  "total_steps": 1746,
  "steps_per_epoch": 97,
  "config": {
    "epochs": 18,
    "batch_size": 512,
    "label_smoothing": 0.2,
    "warmup_frac": 0.1,
    "cutout": 8,
    "ema_decay": 0.995,
    "eval_every": 48,
    "adamw": {
      "lr": 0.003,
      "weight_decay": 0.05,
      "betas": [
        0.9,
        0.95
      ]
    },
    "muon": {
      "lr": 0.03,
      "weight_decay": 0.01,
      "momentum": 0.95,
      "ns_steps": 5
    }
  },
  "env": {
    "torch": "2.12.0+cu126",
    "cuda_available": true,
    "device": "cuda",
    "platform": "nt",
    "gpu": "NVIDIA GeForce RTX 3050 Laptop GPU",
    "vram_gb": 4.0,
    "cuda": "12.6"
  },
  "history": [
    {
      "step": 48,
      "epoch": 0.4948453608247423,
      "train_time_s": 12.296,
      "test_acc": 0.4256,
      "raw_acc": 0.4256,
      "ema_acc": 0.1482,
      "test_loss": 1.6319
    },
    {
      "step": 96,
      "epoch": 0.9896907216494846,
      "train_time_s": 18.515,
      "test_acc": 0.5548,
      "raw_acc": 0.5548,
      "ema_acc": 0.1026,
      "test_loss": 1.257
    },
    {
      "step": 144,
      "epoch": 1.4845360824742269,
      "train_time_s": 24.732,
      "test_acc": 0.6475,
      "raw_acc": 0.6475,
      "ema_acc": 0.1218,
      "test_loss": 1.0674
    },
    {
      "step": 192,
      "epoch": 1.9793814432989691,
      "train_time_s": 30.949,
      "test_acc": 0.6895,
      "raw_acc": 0.6895,
      "ema_acc": 0.2099,
      "test_loss": 0.9793
    },
    {
      "step": 240,
      "epoch": 2.4742268041237114,
      "train_time_s": 37.168,
      "test_acc": 0.7524,
      "raw_acc": 0.7524,
      "ema_acc": 0.2575,
      "test_loss": 0.8493
    },
    {
      "step": 288,
      "epoch": 2.9690721649484537,
      "train_time_s": 43.389,
      "test_acc": 0.7829,
      "raw_acc": 0.7829,
      "ema_acc": 0.3486,
      "test_loss": 0.8042
    },
    {
      "step": 336,
      "epoch": 3.463917525773196,
      "train_time_s": 49.607,
      "test_acc": 0.7362,
      "raw_acc": 0.7362,
      "ema_acc": 0.5158,
      "test_loss": 0.8651
    },
    {
      "step": 384,
      "epoch": 3.9587628865979383,
      "train_time_s": 55.827,
      "test_acc": 0.7937,
      "raw_acc": 0.7937,
      "ema_acc": 0.6486,
      "test_loss": 0.7111
    },
    {
      "step": 432,
      "epoch": 4.453608247422681,
      "train_time_s": 62.045,
      "test_acc": 0.8057,
      "raw_acc": 0.8057,
      "ema_acc": 0.7316,
      "test_loss": 0.7157
    },
    {
      "step": 480,
      "epoch": 4.948453608247423,
      "train_time_s": 68.265,
      "test_acc": 0.8194,
      "raw_acc": 0.8194,
      "ema_acc": 0.7849,
      "test_loss": 0.6495
    },
    {
      "step": 528,
      "epoch": 5.443298969072165,
      "train_time_s": 74.484,
      "test_acc": 0.8283,
      "raw_acc": 0.8283,
      "ema_acc": 0.8178,
      "test_loss": 0.6543
    },
    {
      "step": 576,
      "epoch": 5.938144329896907,
      "train_time_s": 80.702,
      "test_acc": 0.8439,
      "raw_acc": 0.7961,
      "ema_acc": 0.8439,
      "test_loss": 0.7219
    },
    {
      "step": 624,
      "epoch": 6.43298969072165,
      "train_time_s": 86.921,
      "test_acc": 0.8619,
      "raw_acc": 0.8569,
      "ema_acc": 0.8619,
      "test_loss": 0.6187
    },
    {
      "step": 672,
      "epoch": 6.927835051546392,
      "train_time_s": 93.14,
      "test_acc": 0.8729,
      "raw_acc": 0.8645,
      "ema_acc": 0.8729,
      "test_loss": 0.5997
    },
    {
      "step": 720,
      "epoch": 7.422680412371134,
      "train_time_s": 99.354,
      "test_acc": 0.8805,
      "raw_acc": 0.8588,
      "ema_acc": 0.8805,
      "test_loss": 0.5373
    },
    {
      "step": 768,
      "epoch": 7.917525773195877,
      "train_time_s": 105.572,
      "test_acc": 0.8881,
      "raw_acc": 0.8485,
      "ema_acc": 0.8881,
      "test_loss": 0.6315
    },
    {
      "step": 816,
      "epoch": 8.412371134020619,
      "train_time_s": 111.791,
      "test_acc": 0.8921,
      "raw_acc": 0.8755,
      "ema_acc": 0.8921,
      "test_loss": 0.5237
    },
    {
      "step": 864,
      "epoch": 8.907216494845361,
      "train_time_s": 118.012,
      "test_acc": 0.8973,
      "raw_acc": 0.8776,
      "ema_acc": 0.8973,
      "test_loss": 0.51
    },
    {
      "step": 912,
      "epoch": 9.402061855670103,
      "train_time_s": 124.236,
      "test_acc": 0.9013,
      "raw_acc": 0.8702,
      "ema_acc": 0.9013,
      "test_loss": 0.5413
    },
    {
      "step": 960,
      "epoch": 9.896907216494846,
      "train_time_s": 130.485,
      "test_acc": 0.9049,
      "raw_acc": 0.8823,
      "ema_acc": 0.9049,
      "test_loss": 0.53
    },
    {
      "step": 1008,
      "epoch": 10.391752577319588,
      "train_time_s": 136.728,
      "test_acc": 0.9094,
      "raw_acc": 0.8751,
      "ema_acc": 0.9094,
      "test_loss": 0.5501
    },
    {
      "step": 1056,
      "epoch": 10.88659793814433,
      "train_time_s": 142.976,
      "test_acc": 0.9118,
      "raw_acc": 0.896,
      "ema_acc": 0.9118,
      "test_loss": 0.4749
    },
    {
      "step": 1104,
      "epoch": 11.381443298969073,
      "train_time_s": 149.221,
      "test_acc": 0.9148,
      "raw_acc": 0.8857,
      "ema_acc": 0.9148,
      "test_loss": 0.4847
    },
    {
      "step": 1152,
      "epoch": 11.876288659793815,
      "train_time_s": 155.468,
      "test_acc": 0.9168,
      "raw_acc": 0.8972,
      "ema_acc": 0.9168,
      "test_loss": 0.4938
    },
    {
      "step": 1200,
      "epoch": 12.371134020618557,
      "train_time_s": 161.713,
      "test_acc": 0.9187,
      "raw_acc": 0.8975,
      "ema_acc": 0.9187,
      "test_loss": 0.4868
    },
    {
      "step": 1248,
      "epoch": 12.8659793814433,
      "train_time_s": 167.957,
      "test_acc": 0.9194,
      "raw_acc": 0.9096,
      "ema_acc": 0.9194,
      "test_loss": 0.435
    },
    {
      "step": 1296,
      "epoch": 13.360824742268042,
      "train_time_s": 174.201,
      "test_acc": 0.9215,
      "raw_acc": 0.911,
      "ema_acc": 0.9215,
      "test_loss": 0.4603
    },
    {
      "step": 1344,
      "epoch": 13.855670103092784,
      "train_time_s": 180.443,
      "test_acc": 0.9228,
      "raw_acc": 0.9096,
      "ema_acc": 0.9228,
      "test_loss": 0.4257
    },
    {
      "step": 1392,
      "epoch": 14.350515463917526,
      "train_time_s": 186.682,
      "test_acc": 0.9233,
      "raw_acc": 0.9111,
      "ema_acc": 0.9233,
      "test_loss": 0.4459
    },
    {
      "step": 1440,
      "epoch": 14.845360824742269,
      "train_time_s": 192.927,
      "test_acc": 0.9238,
      "raw_acc": 0.919,
      "ema_acc": 0.9238,
      "test_loss": 0.4375
    },
    {
      "step": 1488,
      "epoch": 15.34020618556701,
      "train_time_s": 199.172,
      "test_acc": 0.9242,
      "raw_acc": 0.9176,
      "ema_acc": 0.9242,
      "test_loss": 0.4248
    },
    {
      "step": 1536,
      "epoch": 15.835051546391753,
      "train_time_s": 205.413,
      "test_acc": 0.9256,
      "raw_acc": 0.9192,
      "ema_acc": 0.9256,
      "test_loss": 0.4284
    },
    {
      "step": 1584,
      "epoch": 16.329896907216494,
      "train_time_s": 211.653,
      "test_acc": 0.9263,
      "raw_acc": 0.9233,
      "ema_acc": 0.9263,
      "test_loss": 0.4136
    },
    {
      "step": 1632,
      "epoch": 16.824742268041238,
      "train_time_s": 217.893,
      "test_acc": 0.9267,
      "raw_acc": 0.9245,
      "ema_acc": 0.9267,
      "test_loss": 0.4049
    },
    {
      "step": 1680,
      "epoch": 17.31958762886598,
      "train_time_s": 224.134,
      "test_acc": 0.9273,
      "raw_acc": 0.9273,
      "ema_acc": 0.9269,
      "test_loss": 0.4007
    },
    {
      "step": 1728,
      "epoch": 17.814432989690722,
      "train_time_s": 230.377,
      "test_acc": 0.9278,
      "raw_acc": 0.9278,
      "ema_acc": 0.9275,
      "test_loss": 0.4019
    },
    {
      "step": 1746,
      "epoch": 18.0,
      "train_time_s": 232.72,
      "test_acc": 0.9285,
      "raw_acc": 0.9285,
      "ema_acc": 0.9279,
      "test_loss": 0.3998
    }
  ]
}